/*    */ package com.jcraft.jsch;
/*    */ 
/*    */ 
/*    */ 
/*    */ 
/*    */ 
/*    */ 
/*    */ 
/*    */ 
/*    */ 
/*    */ 
/*    */ 
/*    */ 
/*    */ 
/*    */ 
/*    */ 
/*    */ 
/*    */ 
/*    */ 
/*    */ 
/*    */ 
/*    */ 
/*    */ 
/*    */ 
/*    */ 
/*    */ 
/*    */ 
/*    */ 
/*    */ 
/*    */ class UserAuthPassword
/*    */   extends UserAuth
/*    */ {
/* 33 */   private final int SSH_MSG_USERAUTH_PASSWD_CHANGEREQ = 60;
/*    */   
/*    */   public boolean start(Session session) throws Exception {
/*    */     // Byte code:
/*    */     //   0: aload_0
/*    */     //   1: aload_1
/*    */     //   2: invokespecial start : (Lcom/jcraft/jsch/Session;)Z
/*    */     //   5: pop
/*    */     //   6: aload_1
/*    */     //   7: getfield password : [B
/*    */     //   10: astore_2
/*    */     //   11: new java/lang/StringBuffer
/*    */     //   14: dup
/*    */     //   15: invokespecial <init> : ()V
/*    */     //   18: aload_0
/*    */     //   19: getfield username : Ljava/lang/String;
/*    */     //   22: invokevirtual append : (Ljava/lang/String;)Ljava/lang/StringBuffer;
/*    */     //   25: ldc '@'
/*    */     //   27: invokevirtual append : (Ljava/lang/String;)Ljava/lang/StringBuffer;
/*    */     //   30: aload_1
/*    */     //   31: getfield host : Ljava/lang/String;
/*    */     //   34: invokevirtual append : (Ljava/lang/String;)Ljava/lang/StringBuffer;
/*    */     //   37: invokevirtual toString : ()Ljava/lang/String;
/*    */     //   40: astore_3
/*    */     //   41: aload_1
/*    */     //   42: getfield port : I
/*    */     //   45: bipush #22
/*    */     //   47: if_icmpeq -> 77
/*    */     //   50: new java/lang/StringBuffer
/*    */     //   53: dup
/*    */     //   54: invokespecial <init> : ()V
/*    */     //   57: aload_3
/*    */     //   58: invokevirtual append : (Ljava/lang/String;)Ljava/lang/StringBuffer;
/*    */     //   61: ldc ':'
/*    */     //   63: invokevirtual append : (Ljava/lang/String;)Ljava/lang/StringBuffer;
/*    */     //   66: aload_1
/*    */     //   67: getfield port : I
/*    */     //   70: invokevirtual append : (I)Ljava/lang/StringBuffer;
/*    */     //   73: invokevirtual toString : ()Ljava/lang/String;
/*    */     //   76: astore_3
/*    */     //   77: aload_1
/*    */     //   78: getfield auth_failures : I
/*    */     //   81: aload_1
/*    */     //   82: getfield max_auth_tries : I
/*    */     //   85: if_icmplt -> 104
/*    */     //   88: iconst_0
/*    */     //   89: istore #4
/*    */     //   91: aload_2
/*    */     //   92: ifnull -> 101
/*    */     //   95: aload_2
/*    */     //   96: invokestatic bzero : ([B)V
/*    */     //   99: aconst_null
/*    */     //   100: astore_2
/*    */     //   101: iload #4
/*    */     //   103: ireturn
/*    */     //   104: aload_2
/*    */     //   105: ifnonnull -> 204
/*    */     //   108: aload_0
/*    */     //   109: getfield userinfo : Lcom/jcraft/jsch/UserInfo;
/*    */     //   112: ifnonnull -> 131
/*    */     //   115: iconst_0
/*    */     //   116: istore #4
/*    */     //   118: aload_2
/*    */     //   119: ifnull -> 128
/*    */     //   122: aload_2
/*    */     //   123: invokestatic bzero : ([B)V
/*    */     //   126: aconst_null
/*    */     //   127: astore_2
/*    */     //   128: iload #4
/*    */     //   130: ireturn
/*    */     //   131: aload_0
/*    */     //   132: getfield userinfo : Lcom/jcraft/jsch/UserInfo;
/*    */     //   135: new java/lang/StringBuffer
/*    */     //   138: dup
/*    */     //   139: invokespecial <init> : ()V
/*    */     //   142: ldc 'Password for '
/*    */     //   144: invokevirtual append : (Ljava/lang/String;)Ljava/lang/StringBuffer;
/*    */     //   147: aload_3
/*    */     //   148: invokevirtual append : (Ljava/lang/String;)Ljava/lang/StringBuffer;
/*    */     //   151: invokevirtual toString : ()Ljava/lang/String;
/*    */     //   154: invokeinterface promptPassword : (Ljava/lang/String;)Z
/*    */     //   159: ifne -> 172
/*    */     //   162: new com/jcraft/jsch/JSchAuthCancelException
/*    */     //   165: dup
/*    */     //   166: ldc 'password'
/*    */     //   168: invokespecial <init> : (Ljava/lang/String;)V
/*    */     //   171: athrow
/*    */     //   172: aload_0
/*    */     //   173: getfield userinfo : Lcom/jcraft/jsch/UserInfo;
/*    */     //   176: invokeinterface getPassword : ()Ljava/lang/String;
/*    */     //   181: astore #4
/*    */     //   183: aload #4
/*    */     //   185: ifnonnull -> 198
/*    */     //   188: new com/jcraft/jsch/JSchAuthCancelException
/*    */     //   191: dup
/*    */     //   192: ldc 'password'
/*    */     //   194: invokespecial <init> : (Ljava/lang/String;)V
/*    */     //   197: athrow
/*    */     //   198: aload #4
/*    */     //   200: invokestatic str2byte : (Ljava/lang/String;)[B
/*    */     //   203: astore_2
/*    */     //   204: aconst_null
/*    */     //   205: astore #4
/*    */     //   207: aload_0
/*    */     //   208: getfield username : Ljava/lang/String;
/*    */     //   211: invokestatic str2byte : (Ljava/lang/String;)[B
/*    */     //   214: astore #4
/*    */     //   216: aload_0
/*    */     //   217: getfield packet : Lcom/jcraft/jsch/Packet;
/*    */     //   220: invokevirtual reset : ()V
/*    */     //   223: aload_0
/*    */     //   224: getfield buf : Lcom/jcraft/jsch/Buffer;
/*    */     //   227: bipush #50
/*    */     //   229: invokevirtual putByte : (B)V
/*    */     //   232: aload_0
/*    */     //   233: getfield buf : Lcom/jcraft/jsch/Buffer;
/*    */     //   236: aload #4
/*    */     //   238: invokevirtual putString : ([B)V
/*    */     //   241: aload_0
/*    */     //   242: getfield buf : Lcom/jcraft/jsch/Buffer;
/*    */     //   245: ldc 'ssh-connection'
/*    */     //   247: invokestatic str2byte : (Ljava/lang/String;)[B
/*    */     //   250: invokevirtual putString : ([B)V
/*    */     //   253: aload_0
/*    */     //   254: getfield buf : Lcom/jcraft/jsch/Buffer;
/*    */     //   257: ldc 'password'
/*    */     //   259: invokestatic str2byte : (Ljava/lang/String;)[B
/*    */     //   262: invokevirtual putString : ([B)V
/*    */     //   265: aload_0
/*    */     //   266: getfield buf : Lcom/jcraft/jsch/Buffer;
/*    */     //   269: iconst_0
/*    */     //   270: invokevirtual putByte : (B)V
/*    */     //   273: aload_0
/*    */     //   274: getfield buf : Lcom/jcraft/jsch/Buffer;
/*    */     //   277: aload_2
/*    */     //   278: invokevirtual putString : ([B)V
/*    */     //   281: aload_1
/*    */     //   282: aload_0
/*    */     //   283: getfield packet : Lcom/jcraft/jsch/Packet;
/*    */     //   286: invokevirtual write : (Lcom/jcraft/jsch/Packet;)V
/*    */     //   289: aload_0
/*    */     //   290: aload_1
/*    */     //   291: aload_0
/*    */     //   292: getfield buf : Lcom/jcraft/jsch/Buffer;
/*    */     //   295: invokevirtual read : (Lcom/jcraft/jsch/Buffer;)Lcom/jcraft/jsch/Buffer;
/*    */     //   298: putfield buf : Lcom/jcraft/jsch/Buffer;
/*    */     //   301: aload_0
/*    */     //   302: getfield buf : Lcom/jcraft/jsch/Buffer;
/*    */     //   305: invokevirtual getCommand : ()B
/*    */     //   308: sipush #255
/*    */     //   311: iand
/*    */     //   312: istore #5
/*    */     //   314: iload #5
/*    */     //   316: bipush #52
/*    */     //   318: if_icmpne -> 337
/*    */     //   321: iconst_1
/*    */     //   322: istore #6
/*    */     //   324: aload_2
/*    */     //   325: ifnull -> 334
/*    */     //   328: aload_2
/*    */     //   329: invokestatic bzero : ([B)V
/*    */     //   332: aconst_null
/*    */     //   333: astore_2
/*    */     //   334: iload #6
/*    */     //   336: ireturn
/*    */     //   337: iload #5
/*    */     //   339: bipush #53
/*    */     //   341: if_icmpne -> 414
/*    */     //   344: aload_0
/*    */     //   345: getfield buf : Lcom/jcraft/jsch/Buffer;
/*    */     //   348: invokevirtual getInt : ()I
/*    */     //   351: pop
/*    */     //   352: aload_0
/*    */     //   353: getfield buf : Lcom/jcraft/jsch/Buffer;
/*    */     //   356: invokevirtual getByte : ()I
/*    */     //   359: pop
/*    */     //   360: aload_0
/*    */     //   361: getfield buf : Lcom/jcraft/jsch/Buffer;
/*    */     //   364: invokevirtual getByte : ()I
/*    */     //   367: pop
/*    */     //   368: aload_0
/*    */     //   369: getfield buf : Lcom/jcraft/jsch/Buffer;
/*    */     //   372: invokevirtual getString : ()[B
/*    */     //   375: astore #6
/*    */     //   377: aload_0
/*    */     //   378: getfield buf : Lcom/jcraft/jsch/Buffer;
/*    */     //   381: invokevirtual getString : ()[B
/*    */     //   384: astore #7
/*    */     //   386: aload #6
/*    */     //   388: invokestatic byte2str : ([B)Ljava/lang/String;
/*    */     //   391: astore #8
/*    */     //   393: aload_0
/*    */     //   394: getfield userinfo : Lcom/jcraft/jsch/UserInfo;
/*    */     //   397: ifnull -> 289
/*    */     //   400: aload_0
/*    */     //   401: getfield userinfo : Lcom/jcraft/jsch/UserInfo;
/*    */     //   404: aload #8
/*    */     //   406: invokeinterface showMessage : (Ljava/lang/String;)V
/*    */     //   411: goto -> 289
/*    */     //   414: iload #5
/*    */     //   416: bipush #60
/*    */     //   418: if_icmpne -> 685
/*    */     //   421: aload_0
/*    */     //   422: getfield buf : Lcom/jcraft/jsch/Buffer;
/*    */     //   425: invokevirtual getInt : ()I
/*    */     //   428: pop
/*    */     //   429: aload_0
/*    */     //   430: getfield buf : Lcom/jcraft/jsch/Buffer;
/*    */     //   433: invokevirtual getByte : ()I
/*    */     //   436: pop
/*    */     //   437: aload_0
/*    */     //   438: getfield buf : Lcom/jcraft/jsch/Buffer;
/*    */     //   441: invokevirtual getByte : ()I
/*    */     //   444: pop
/*    */     //   445: aload_0
/*    */     //   446: getfield buf : Lcom/jcraft/jsch/Buffer;
/*    */     //   449: invokevirtual getString : ()[B
/*    */     //   452: astore #6
/*    */     //   454: aload_0
/*    */     //   455: getfield buf : Lcom/jcraft/jsch/Buffer;
/*    */     //   458: invokevirtual getString : ()[B
/*    */     //   461: astore #7
/*    */     //   463: aload_0
/*    */     //   464: getfield userinfo : Lcom/jcraft/jsch/UserInfo;
/*    */     //   467: ifnull -> 480
/*    */     //   470: aload_0
/*    */     //   471: getfield userinfo : Lcom/jcraft/jsch/UserInfo;
/*    */     //   474: instanceof com/jcraft/jsch/UIKeyboardInteractive
/*    */     //   477: ifne -> 514
/*    */     //   480: aload_0
/*    */     //   481: getfield userinfo : Lcom/jcraft/jsch/UserInfo;
/*    */     //   484: ifnull -> 498
/*    */     //   487: aload_0
/*    */     //   488: getfield userinfo : Lcom/jcraft/jsch/UserInfo;
/*    */     //   491: ldc 'Password must be changed.'
/*    */     //   493: invokeinterface showMessage : (Ljava/lang/String;)V
/*    */     //   498: iconst_0
/*    */     //   499: istore #8
/*    */     //   501: aload_2
/*    */     //   502: ifnull -> 511
/*    */     //   505: aload_2
/*    */     //   506: invokestatic bzero : ([B)V
/*    */     //   509: aconst_null
/*    */     //   510: astore_2
/*    */     //   511: iload #8
/*    */     //   513: ireturn
/*    */     //   514: aload_0
/*    */     //   515: getfield userinfo : Lcom/jcraft/jsch/UserInfo;
/*    */     //   518: checkcast com/jcraft/jsch/UIKeyboardInteractive
/*    */     //   521: astore #8
/*    */     //   523: ldc 'Password Change Required'
/*    */     //   525: astore #10
/*    */     //   527: iconst_1
/*    */     //   528: anewarray java/lang/String
/*    */     //   531: dup
/*    */     //   532: iconst_0
/*    */     //   533: ldc 'New Password: '
/*    */     //   535: aastore
/*    */     //   536: astore #11
/*    */     //   538: iconst_1
/*    */     //   539: newarray boolean
/*    */     //   541: dup
/*    */     //   542: iconst_0
/*    */     //   543: iconst_0
/*    */     //   544: bastore
/*    */     //   545: astore #12
/*    */     //   547: aload #8
/*    */     //   549: aload_3
/*    */     //   550: aload #10
/*    */     //   552: aload #6
/*    */     //   554: invokestatic byte2str : ([B)Ljava/lang/String;
/*    */     //   557: aload #11
/*    */     //   559: aload #12
/*    */     //   561: invokeinterface promptKeyboardInteractive : (Ljava/lang/String;Ljava/lang/String;Ljava/lang/String;[Ljava/lang/String;[Z)[Ljava/lang/String;
/*    */     //   566: astore #9
/*    */     //   568: aload #9
/*    */     //   570: ifnonnull -> 583
/*    */     //   573: new com/jcraft/jsch/JSchAuthCancelException
/*    */     //   576: dup
/*    */     //   577: ldc 'password'
/*    */     //   579: invokespecial <init> : (Ljava/lang/String;)V
/*    */     //   582: athrow
/*    */     //   583: aload #9
/*    */     //   585: iconst_0
/*    */     //   586: aaload
/*    */     //   587: invokestatic str2byte : (Ljava/lang/String;)[B
/*    */     //   590: astore #13
/*    */     //   592: aload_0
/*    */     //   593: getfield packet : Lcom/jcraft/jsch/Packet;
/*    */     //   596: invokevirtual reset : ()V
/*    */     //   599: aload_0
/*    */     //   600: getfield buf : Lcom/jcraft/jsch/Buffer;
/*    */     //   603: bipush #50
/*    */     //   605: invokevirtual putByte : (B)V
/*    */     //   608: aload_0
/*    */     //   609: getfield buf : Lcom/jcraft/jsch/Buffer;
/*    */     //   612: aload #4
/*    */     //   614: invokevirtual putString : ([B)V
/*    */     //   617: aload_0
/*    */     //   618: getfield buf : Lcom/jcraft/jsch/Buffer;
/*    */     //   621: ldc 'ssh-connection'
/*    */     //   623: invokestatic str2byte : (Ljava/lang/String;)[B
/*    */     //   626: invokevirtual putString : ([B)V
/*    */     //   629: aload_0
/*    */     //   630: getfield buf : Lcom/jcraft/jsch/Buffer;
/*    */     //   633: ldc 'password'
/*    */     //   635: invokestatic str2byte : (Ljava/lang/String;)[B
/*    */     //   638: invokevirtual putString : ([B)V
/*    */     //   641: aload_0
/*    */     //   642: getfield buf : Lcom/jcraft/jsch/Buffer;
/*    */     //   645: iconst_1
/*    */     //   646: invokevirtual putByte : (B)V
/*    */     //   649: aload_0
/*    */     //   650: getfield buf : Lcom/jcraft/jsch/Buffer;
/*    */     //   653: aload_2
/*    */     //   654: invokevirtual putString : ([B)V
/*    */     //   657: aload_0
/*    */     //   658: getfield buf : Lcom/jcraft/jsch/Buffer;
/*    */     //   661: aload #13
/*    */     //   663: invokevirtual putString : ([B)V
/*    */     //   666: aload #13
/*    */     //   668: invokestatic bzero : ([B)V
/*    */     //   671: aconst_null
/*    */     //   672: astore #9
/*    */     //   674: aload_1
/*    */     //   675: aload_0
/*    */     //   676: getfield packet : Lcom/jcraft/jsch/Packet;
/*    */     //   679: invokevirtual write : (Lcom/jcraft/jsch/Packet;)V
/*    */     //   682: goto -> 289
/*    */     //   685: iload #5
/*    */     //   687: bipush #51
/*    */     //   689: if_icmpne -> 765
/*    */     //   692: aload_0
/*    */     //   693: getfield buf : Lcom/jcraft/jsch/Buffer;
/*    */     //   696: invokevirtual getInt : ()I
/*    */     //   699: pop
/*    */     //   700: aload_0
/*    */     //   701: getfield buf : Lcom/jcraft/jsch/Buffer;
/*    */     //   704: invokevirtual getByte : ()I
/*    */     //   707: pop
/*    */     //   708: aload_0
/*    */     //   709: getfield buf : Lcom/jcraft/jsch/Buffer;
/*    */     //   712: invokevirtual getByte : ()I
/*    */     //   715: pop
/*    */     //   716: aload_0
/*    */     //   717: getfield buf : Lcom/jcraft/jsch/Buffer;
/*    */     //   720: invokevirtual getString : ()[B
/*    */     //   723: astore #6
/*    */     //   725: aload_0
/*    */     //   726: getfield buf : Lcom/jcraft/jsch/Buffer;
/*    */     //   729: invokevirtual getByte : ()I
/*    */     //   732: istore #7
/*    */     //   734: iload #7
/*    */     //   736: ifeq -> 752
/*    */     //   739: new com/jcraft/jsch/JSchPartialAuthException
/*    */     //   742: dup
/*    */     //   743: aload #6
/*    */     //   745: invokestatic byte2str : ([B)Ljava/lang/String;
/*    */     //   748: invokespecial <init> : (Ljava/lang/String;)V
/*    */     //   751: athrow
/*    */     //   752: aload_1
/*    */     //   753: dup
/*    */     //   754: getfield auth_failures : I
/*    */     //   757: iconst_1
/*    */     //   758: iadd
/*    */     //   759: putfield auth_failures : I
/*    */     //   762: goto -> 781
/*    */     //   765: iconst_0
/*    */     //   766: istore #6
/*    */     //   768: aload_2
/*    */     //   769: ifnull -> 778
/*    */     //   772: aload_2
/*    */     //   773: invokestatic bzero : ([B)V
/*    */     //   776: aconst_null
/*    */     //   777: astore_2
/*    */     //   778: iload #6
/*    */     //   780: ireturn
/*    */     //   781: aload_2
/*    */     //   782: ifnull -> 791
/*    */     //   785: aload_2
/*    */     //   786: invokestatic bzero : ([B)V
/*    */     //   789: aconst_null
/*    */     //   790: astore_2
/*    */     //   791: goto -> 77
/*    */     //   794: astore #14
/*    */     //   796: aload_2
/*    */     //   797: ifnull -> 806
/*    */     //   800: aload_2
/*    */     //   801: invokestatic bzero : ([B)V
/*    */     //   804: aconst_null
/*    */     //   805: astore_2
/*    */     //   806: aload #14
/*    */     //   808: athrow
/*    */     // Line number table:
/*    */     //   Java source line number -> byte code offset
/*    */     //   #36	-> 0
/*    */     //   #38	-> 6
/*    */     //   #39	-> 11
/*    */     //   #40	-> 41
/*    */     //   #41	-> 50
/*    */     //   #48	-> 77
/*    */     //   #49	-> 88
/*    */     //   #184	-> 91
/*    */     //   #185	-> 95
/*    */     //   #186	-> 99
/*    */     //   #52	-> 104
/*    */     //   #53	-> 108
/*    */     //   #55	-> 115
/*    */     //   #184	-> 118
/*    */     //   #185	-> 122
/*    */     //   #186	-> 126
/*    */     //   #57	-> 131
/*    */     //   #58	-> 162
/*    */     //   #62	-> 172
/*    */     //   #63	-> 183
/*    */     //   #64	-> 188
/*    */     //   #67	-> 198
/*    */     //   #70	-> 204
/*    */     //   #71	-> 207
/*    */     //   #80	-> 216
/*    */     //   #81	-> 223
/*    */     //   #82	-> 232
/*    */     //   #83	-> 241
/*    */     //   #84	-> 253
/*    */     //   #85	-> 265
/*    */     //   #86	-> 273
/*    */     //   #87	-> 281
/*    */     //   #91	-> 289
/*    */     //   #92	-> 301
/*    */     //   #94	-> 314
/*    */     //   #95	-> 321
/*    */     //   #184	-> 324
/*    */     //   #185	-> 328
/*    */     //   #186	-> 332
/*    */     //   #97	-> 337
/*    */     //   #98	-> 344
/*    */     //   #99	-> 368
/*    */     //   #100	-> 377
/*    */     //   #101	-> 386
/*    */     //   #102	-> 393
/*    */     //   #103	-> 400
/*    */     //   #107	-> 414
/*    */     //   #108	-> 421
/*    */     //   #109	-> 445
/*    */     //   #110	-> 454
/*    */     //   #111	-> 463
/*    */     //   #113	-> 480
/*    */     //   #114	-> 487
/*    */     //   #116	-> 498
/*    */     //   #184	-> 501
/*    */     //   #185	-> 505
/*    */     //   #186	-> 509
/*    */     //   #119	-> 514
/*    */     //   #121	-> 523
/*    */     //   #122	-> 527
/*    */     //   #123	-> 538
/*    */     //   #124	-> 547
/*    */     //   #129	-> 568
/*    */     //   #130	-> 573
/*    */     //   #133	-> 583
/*    */     //   #143	-> 592
/*    */     //   #144	-> 599
/*    */     //   #145	-> 608
/*    */     //   #146	-> 617
/*    */     //   #147	-> 629
/*    */     //   #148	-> 641
/*    */     //   #149	-> 649
/*    */     //   #150	-> 657
/*    */     //   #151	-> 666
/*    */     //   #152	-> 671
/*    */     //   #153	-> 674
/*    */     //   #154	-> 682
/*    */     //   #156	-> 685
/*    */     //   #157	-> 692
/*    */     //   #158	-> 716
/*    */     //   #159	-> 725
/*    */     //   #162	-> 734
/*    */     //   #163	-> 739
/*    */     //   #165	-> 752
/*    */     //   #166	-> 762
/*    */     //   #171	-> 765
/*    */     //   #184	-> 768
/*    */     //   #185	-> 772
/*    */     //   #186	-> 776
/*    */     //   #175	-> 781
/*    */     //   #176	-> 785
/*    */     //   #177	-> 789
/*    */     //   #180	-> 791
/*    */     //   #184	-> 794
/*    */     //   #185	-> 800
/*    */     //   #186	-> 804
/*    */     // Local variable table:
/*    */     //   start	length	slot	name	descriptor
/*    */     //   183	21	4	_password	Ljava/lang/String;
/*    */     //   377	37	6	_message	[B
/*    */     //   386	28	7	lang	[B
/*    */     //   393	21	8	message	Ljava/lang/String;
/*    */     //   454	231	6	instruction	[B
/*    */     //   463	222	7	tag	[B
/*    */     //   523	162	8	kbi	Lcom/jcraft/jsch/UIKeyboardInteractive;
/*    */     //   568	117	9	response	[Ljava/lang/String;
/*    */     //   527	158	10	name	Ljava/lang/String;
/*    */     //   538	147	11	prompt	[Ljava/lang/String;
/*    */     //   547	138	12	echo	[Z
/*    */     //   592	93	13	newpassword	[B
/*    */     //   725	40	6	foo	[B
/*    */     //   734	31	7	partial_success	I
/*    */     //   314	467	5	command	I
/*    */     //   207	584	4	_username	[B
/*    */     //   0	809	0	this	Lcom/jcraft/jsch/UserAuthPassword;
/*    */     //   0	809	1	session	Lcom/jcraft/jsch/Session;
/*    */     //   11	798	2	password	[B
/*    */     //   41	768	3	dest	Ljava/lang/String;
/*    */     // Exception table:
/*    */     //   from	to	target	type
/*    */     //   77	91	794	finally
/*    */     //   104	118	794	finally
/*    */     //   131	324	794	finally
/*    */     //   337	501	794	finally
/*    */     //   514	768	794	finally
/*    */     //   781	796	794	finally
/*    */   }
/*    */ }


/* Location:              F:\JAVA\ISGlobalServices.jar!\com\jcraft\jsch\UserAuthPassword.class
 * Java compiler version: 4 (48.0)
 * JD-Core Version:       1.1.3
 */